mpytool/__init__.py
mpytool/conn.py
mpytool/conn_serial.py
mpytool/conn_socket.py
mpytool/logger.py
mpytool/mpy.py
mpytool/mpy_comm.py
mpytool/mpytool.py
mpytool/terminal.py
mpytool/utils.py
mpytool-2.0.0.dist-info/licenses/LICENSE
mpytool-2.0.0.dist-info/METADATA
mpytool-2.0.0.dist-info/WHEEL
mpytool-2.0.0.dist-info/entry_points.txt
mpytool-2.0.0.dist-info/top_level.txt
mpytool-2.0.0.dist-info/RECORD
