Metadata-Version: 2.4
Name: mpytool
Version: 2.0.0
Summary: MPY tool - manage files on devices running MicroPython
Author-email: Pavel Revak <pavel.revak@gmail.com>
License-Expression: MIT
Project-URL: Homepage, https://github.com/pavelrevak/mpytool
Keywords: MPY,micropython
Requires-Python: >=3.10
License-File: LICENSE
Requires-Dist: pyserial>=3.0
Dynamic: license-file
